redditcleaner/__init__.py
redditcleaner-1.1.2.dist-info/LICENSE
redditcleaner-1.1.2.dist-info/METADATA
redditcleaner-1.1.2.dist-info/WHEEL
redditcleaner-1.1.2.dist-info/top_level.txt
redditcleaner-1.1.2.dist-info/RECORD
