Metadata-Version: 2.1
Name: redditcleaner
Version: 1.1.2
Summary: Clean Reddit Text Data
Home-page: https://github.com/lolei/redditcleaner
Author: Lorenz Leitner
Author-email: lrnz.ltnr@gmail.com
License: UNKNOWN
Platform: UNKNOWN
Classifier: Programming Language :: Python :: 3.8
Classifier: License :: OSI Approved :: MIT License
Classifier: Operating System :: OS Independent
Requires-Python: >=3
